bt-tracker-utils/TrackerQueryException.py
bt-tracker-utils/__init__.py
bt-tracker-utils/check_tracker.py
bt-tracker-utils/query.py
bt_tracker_utils/Torrent.py
bt_tracker_utils/TrackerEvent.py
bt_tracker_utils/TrackerQueryException.py
bt_tracker_utils/__init__.py
bt_tracker_utils/check_tracker.py
bt_tracker_utils/query.py
bt_tracker_utils/Peer/Peer.py
bt_tracker_utils/Peer/PeerCommunicationException.py
bt_tracker_utils/Peer/__init__.py
bt_tracker_utils/tracker/Check.py
bt_tracker_utils/tracker/Query.py
bt_tracker_utils/tracker/TrackerQueryException.py
bt_tracker_utils/tracker/__init__.py
torrentlib/Torrent.py
torrentlib/__init__.py
torrentlib/Peer/Peer.py
torrentlib/Peer/PeerCommunicationException.py
torrentlib/Peer/__init__.py
torrentlib/Tracker/Check.py
torrentlib/Tracker/Query.py
torrentlib/Tracker/TrackerQueryException.py
torrentlib/Tracker/__init__.py
torrentlib-1.0.0.dist-info/licenses/LICENSE
torrentlib-1.0.0.dist-info/METADATA
torrentlib-1.0.0.dist-info/WHEEL
torrentlib-1.0.0.dist-info/top_level.txt
torrentlib-1.0.0.dist-info/RECORD
