Metadata-Version: 2.4
Name: torrentlib
Version: 1.0.0
Summary: BitTorrent utilities for querying trackers and peers
Author: JackyHe398
Author-email: hekinghung@gmail.com
Requires-Python: >=3.6
License-File: LICENSE
Requires-Dist: requests>=2.32.4
Requires-Dist: bencodepy>=0.9.5
Requires-Dist: urllib3>=2.5.0
Requires-Dist: humanize>=4.9.0
Requires-Dist: torrent-parser>=0.7.0
Dynamic: author
Dynamic: author-email
Dynamic: description
Dynamic: description-content-type
Dynamic: license-file
Dynamic: requires-dist
Dynamic: requires-python
Dynamic: summary
